tor_proxy/__init__.py
tor_proxy/__main__.py
tor_proxy/common.py
tor_proxy/onion.py
tor_proxy/onionstart.py
tor_proxy/settings.py
tor_proxy/tor_proxy.py
tor_proxy/torrc_template
tor_proxy/torrc_template-windows
tor_proxy-0.0.4.dist-info/licenses/LICENSE
tor_proxy-0.0.4.dist-info/METADATA
tor_proxy-0.0.4.dist-info/WHEEL
tor_proxy-0.0.4.dist-info/entry_points.txt
tor_proxy-0.0.4.dist-info/top_level.txt
tor_proxy-0.0.4.dist-info/RECORD
