Metadata-Version: 2.4
Name: tor-proxy
Version: 0.0.4
Summary: A simple way to send your requests with tor using tor-proxy.
Home-page: https://github.com/jakbin/tor-proxy
Author: Jak Bin
License: MIT License
Project-URL: Bug Tracker, https://github.com/jakbin/tor-proxy/issues
Keywords: flask,tor,onion,stem,proxy,tor-proxy
Classifier: Development Status :: 4 - Beta
Classifier: Programming Language :: Python :: 3.6
Classifier: License :: OSI Approved :: MIT License
Classifier: Operating System :: OS Independent
Requires-Python: >=3
License-File: LICENSE
Requires-Dist: stem
Dynamic: author
Dynamic: classifier
Dynamic: description
Dynamic: description-content-type
Dynamic: home-page
Dynamic: keywords
Dynamic: license
Dynamic: license-file
Dynamic: project-url
Dynamic: requires-dist
Dynamic: requires-python
Dynamic: summary
